jupyter_fdc3_widgets/__init__.py
jupyter_fdc3_widgets/_frontend.py
jupyter_fdc3_widgets/_version.py
jupyter_fdc3_widgets/fdc3_channel_join.py
jupyter_fdc3_widgets/fdc3_connection_status.py
jupyter_fdc3_widgets/fdc3_context_display.py
jupyter_fdc3_widgets/fdc3_raise_intent.py
jupyter_fdc3_widgets/fdc3_ticker_input.py
jupyter_fdc3_widgets/fdc3_version.py
jupyter_fdc3_widgets/labextension/package.json
jupyter_fdc3_widgets/labextension/static/294.520cbde43b7b90c1d6cb.js
jupyter_fdc3_widgets/labextension/static/294.520cbde43b7b90c1d6cb.js.LICENSE.txt
jupyter_fdc3_widgets/labextension/static/387.86e708d8150730738c90.js
jupyter_fdc3_widgets/labextension/static/457.e51fff783104e5af4d11.js
jupyter_fdc3_widgets/labextension/static/457.e51fff783104e5af4d11.js.LICENSE.txt
jupyter_fdc3_widgets/labextension/static/480.d9f860ac86048c9318af.js
jupyter_fdc3_widgets/labextension/static/568.6d9abae2e496bd7a16ef.js
jupyter_fdc3_widgets/labextension/static/935.017ac1e355ab4f688cec.js
jupyter_fdc3_widgets/labextension/static/935.017ac1e355ab4f688cec.js.LICENSE.txt
jupyter_fdc3_widgets/labextension/static/remoteEntry.e32a87f877840e0c4d68.js
jupyter_fdc3_widgets/labextension/static/style.js
jupyter_fdc3_widgets/labextension/static/third-party-licenses.json
jupyter_fdc3_widgets/nbextension/extension.js
jupyter_fdc3_widgets/nbextension/index.js
jupyter_fdc3_widgets/nbextension/index.js.LICENSE.txt
jupyter_fdc3_widgets/nbextension/index.js.map
jupyter_fdc3_widgets/tests/__init__.py
jupyter_fdc3_widgets/tests/conftest.py
jupyter_fdc3_widgets/tests/test_nbextension_path.py
jupyter_fdc3_widgets-0.1.0.data/data/share/jupyter/labextensions/jupyter_fdc3_widgets/package.json
jupyter_fdc3_widgets-0.1.0.data/data/share/jupyter/labextensions/jupyter_fdc3_widgets/static/294.520cbde43b7b90c1d6cb.js
jupyter_fdc3_widgets-0.1.0.data/data/share/jupyter/labextensions/jupyter_fdc3_widgets/static/294.520cbde43b7b90c1d6cb.js.LICENSE.txt
jupyter_fdc3_widgets-0.1.0.dist-info/METADATA
jupyter_fdc3_widgets-0.1.0.dist-info/WHEEL
jupyter_fdc3_widgets-0.1.0.dist-info/licenses/LICENSE
jupyter_fdc3_widgets-0.1.0.dist-info/licenses/LICENSE.spdx
jupyter_fdc3_widgets-0.1.0.dist-info/licenses/LICENSE.txt
jupyter_fdc3_widgets-0.1.0.dist-info/licenses/NOTICE
jupyter_fdc3_widgets-0.1.0.dist-info/RECORD
